ShindenPy/__init__.py
ShindenPy/shinden.py
ShindenPy-0.0.7.dist-info/LICENSE
ShindenPy-0.0.7.dist-info/METADATA
ShindenPy-0.0.7.dist-info/WHEEL
ShindenPy-0.0.7.dist-info/top_level.txt
ShindenPy-0.0.7.dist-info/RECORD
