Metadata-Version: 2.1
Name: ShindenPy
Version: 0.0.7
Summary: Python API for shinden.pl.
Home-page: https://github.com/iLikeTrioxin/ShindenPy/
Author: iLikeTrioxin
Author-email: iLikeTrioxin@protonmail.com
License: GNU Affero General Public License v3
Project-URL: Bug Tracker, https://github.com/iLikeTrioxin/BetterShinden/issuesPy/
Classifier: Programming Language :: Python :: 3
Classifier: License :: OSI Approved :: GNU Affero General Public License v3
Classifier: Operating System :: OS Independent
Requires-Python: >=3.6
License-File: LICENSE
Requires-Dist: bs4
Requires-Dist: aiohttp
Requires-Dist: asyncio
